odoo/addons/web_hide_user_menu_item/README.rst
odoo/addons/web_hide_user_menu_item/__init__.py
odoo/addons/web_hide_user_menu_item/__manifest__.py
odoo/addons/web_hide_user_menu_item/i18n/web_hide_user_menu_item.pot
odoo/addons/web_hide_user_menu_item/readme/CONTRIBUTORS.rst
odoo/addons/web_hide_user_menu_item/readme/DESCRIPTION.rst
odoo/addons/web_hide_user_menu_item/readme/USAGE.rst
odoo/addons/web_hide_user_menu_item/static/description/icon.png
odoo/addons/web_hide_user_menu_item/static/description/index.html
odoo/addons/web_hide_user_menu_item/static/img/userscreen.png
odoo/addons/web_hide_user_menu_item/static/src/webclient/user_menu/user_menu.xml
odoo_addon_web_hide_user_menu_item-15.0.1.0.0.2.dist-info/METADATA
odoo_addon_web_hide_user_menu_item-15.0.1.0.0.2.dist-info/WHEEL
odoo_addon_web_hide_user_menu_item-15.0.1.0.0.2.dist-info/top_level.txt
odoo_addon_web_hide_user_menu_item-15.0.1.0.0.2.dist-info/RECORD
